.hgignore
CHANGES.txt
LICENSE.txt
MANIFEST.in
README.txt
bootstrap.sh
buildout.cfg
setup.py
js/__init__.py
js.ehynds_multiselect.egg-info/PKG-INFO
js.ehynds_multiselect.egg-info/SOURCES.txt
js.ehynds_multiselect.egg-info/dependency_links.txt
js.ehynds_multiselect.egg-info/entry_points.txt
js.ehynds_multiselect.egg-info/namespace_packages.txt
js.ehynds_multiselect.egg-info/not-zip-safe
js.ehynds_multiselect.egg-info/requires.txt
js.ehynds_multiselect.egg-info/top_level.txt
js/ehynds_multiselect/__init__.py
js/ehynds_multiselect/test_multiselect.txt
js/ehynds_multiselect/resources/jquery.multiselect.css
js/ehynds_multiselect/resources/jquery.multiselect.js
js/ehynds_multiselect/resources/jquery.multiselect.min.css
js/ehynds_multiselect/resources/jquery.multiselect.min.js