Metadata-Version: 1.0
Name: js.ehynds-multiselect
Version: 1.13
Summary: Fanstatic packaging of ehynds/jquery-ui-multiselect-widget
Home-page: https://bitbucket.org/gocept/js.ehynds_multiselect
Author: gocept Developers
Author-email: mail@gocept.com
License: BSD
Platform: UNKNOWN
